{"cameraMode":{"drawMode":0,"name":"Shaded","section":"Shading Mode"},"sceneLighting":true,"audioPlay":false,"sceneViewState":{"m_AlwaysRefresh":false,"showFog":true,"showSkybox":true,"showFlares":true,"showImageEffects":true,"showParticleSystems":true,"showVisualEffectGraphs":true,"m_FxEnabled":true},"in2DMode":false,"pivot":{"x":-3.5310230255126955,"y":5.3798065185546879,"z":10.282306671142579},"rotation":{"x":0.1829371601343155,"y":-0.25337880849838259,"z":0.04886121302843094,"w":0.948655366897583},"size":38.1684684753418,"orthographic":false}